__init__.py
main.py
intentioanl_vulnerability-5.0.0.dist-info/LICENSE
intentioanl_vulnerability-5.0.0.dist-info/METADATA
intentioanl_vulnerability-5.0.0.dist-info/WHEEL
intentioanl_vulnerability-5.0.0.dist-info/top_level.txt
intentioanl_vulnerability-5.0.0.dist-info/RECORD
