Metadata-Version: 2.1
Name: intentioanl-vulnerability
Version: 5.0.0
Summary: Intentional inherit
Author-email: Example Author <author@example.com>
Classifier: Programming Language :: Python :: 3
Classifier: License :: OSI Approved :: MIT License
Classifier: Operating System :: OS Independent
Requires-Python: >=3.8
License-File: LICENSE
Requires-Dist: safety >=3.2.4
Requires-Dist: uvicorn >=0.30.1
